kpireport_s3/__init__.py
kpireport_s3/output.py
kpireport_s3-0.0.1.dist-info/METADATA
kpireport_s3-0.0.1.dist-info/WHEEL
kpireport_s3-0.0.1.dist-info/entry_points.txt
kpireport_s3-0.0.1.dist-info/top_level.txt
kpireport_s3-0.0.1.dist-info/RECORD
